cvxsimulator/__init__.py
cvxsimulator/builder.py
cvxsimulator/portfolio.py
cvxsimulator/state.py
cvxsimulator/utils/__init__.py
cvxsimulator/utils/interpolation.py
cvxsimulator-1.4.4.dist-info/METADATA
cvxsimulator-1.4.4.dist-info/WHEEL
cvxsimulator-1.4.4.dist-info/licenses/LICENSE
cvxsimulator-1.4.4.dist-info/RECORD
