Metadata-Version: 2.4
Name: cvxsimulator
Version: 1.4.4
Summary: Simple simulator for investors
Project-URL: repository, https://github.com/cvxgrp/simulator
Author-email: Thomas Schmelzer <thomas.schmelzer@gmail.com>
License-File: LICENSE
Requires-Python: >=3.11
Requires-Dist: jquantstats>=0.0.23
Requires-Dist: numpy>=2.0
Requires-Dist: pandas>=2.2.3
Requires-Dist: polars>=1.24.0
Provides-Extra: dev
Requires-Dist: clarabel>=0.9.0; extra == 'dev'
Requires-Dist: cvxpy-base>=1.5.1; extra == 'dev'
Requires-Dist: loguru; extra == 'dev'
Requires-Dist: marimo>=0.13.15; extra == 'dev'
Requires-Dist: pre-commit>=4.0.1; extra == 'dev'
Requires-Dist: pytest-cov>=6.0.0; extra == 'dev'
Requires-Dist: pytest>=8.3.3; extra == 'dev'
Requires-Dist: python-dotenv==1.1.1; extra == 'dev'
Requires-Dist: tinycta; extra == 'dev'
